Furious/Version.py
Furious/__init__.py
Furious/__main__.py
Furious/Core/CoreManager.py
Furious/Core/CoreProcessWorker.py
Furious/Core/Hysteria1.py
Furious/Core/Hysteria2.py
Furious/Core/Tun2socks.py
Furious/Core/XrayCore.py
Furious/Core/__init__.py
Furious/Data/font/CascadiaMono
Furious/Data/font/LICENSE
Furious/Data/hysteria/bypass-Iran.acl
Furious/Data/hysteria/bypass-mainland-China.acl
Furious/Data/hysteria/country.mmdb
Furious/Data/xray/geoip.dat
Furious/Data/xray/geosite.dat
Furious/Externals/GenTranslation.py
Furious/Externals/__init__.py
Furious/Frozenlib/AppResources.py
Furious/Frozenlib/AppSettings.py
Furious/Frozenlib/Constants.py
Furious/Frozenlib/Enum.py
Furious/Frozenlib/Globals.py
Furious/Frozenlib/Mixins.py
Furious/Frozenlib/PySide6Legacy.py
Furious/Frozenlib/StartupOnBoot.py
Furious/Frozenlib/SystemProxy.py
Furious/Frozenlib/SystemRoutingTable.py
Furious/Frozenlib/SystemRuntime.py
Furious/Frozenlib/Tcping.py
Furious/Frozenlib/Utility.py
Furious/Frozenlib/Win32Session.py
Furious/Frozenlib/__init__.py
Furious/Interface/ApplicationFactory.py
Furious/Interface/ConfigFactory.py
Furious/Interface/CoreProcessFactory.py
Furious/Interface/EncoderFactory.py
Furious/Interface/GuiEditorItemFactory.py
Furious/Interface/StorageFactory.py
Furious/Interface/UserServersTableItem.py
Furious/Interface/__init__.py
Furious/Library/Configuration.py
Furious/Library/Encoder.py
Furious/Library/Storage.py
Furious/Library/UserServers.py
Furious/Library/UserSubs.py
Furious/Library/UserTUNSettings.py
Furious/Library/__init__.py
Furious/Qt/DNSResolver.py
Furious/Qt/DynamicTheme.py
Furious/Qt/DynamicTranslate.py
Furious/Qt/GuiEditorXXX.py
Furious/Qt/NetworkStateManager.py
Furious/Qt/QtGui.py
Furious/Qt/QtNetwork.py
Furious/Qt/QtWidgets.py
Furious/Qt/TextEditor.py
Furious/Qt/TextEditorTheme.py
Furious/Qt/UpdatesManager.py
Furious/Qt/WebGETManager.py
Furious/Qt/XrayAssetDownloadManager.py
Furious/Qt/__init__.py
Furious/TrayActions/Connect.py
Furious/TrayActions/EditConfiguration.py
furious_gui-0.6.1.dist-info/licenses/LICENSE
furious_gui-0.6.1.dist-info/licenses/LICENSE.rtf
furious_gui-0.6.1.dist-info/METADATA
furious_gui-0.6.1.dist-info/WHEEL
furious_gui-0.6.1.dist-info/entry_points.txt
furious_gui-0.6.1.dist-info/top_level.txt
furious_gui-0.6.1.dist-info/RECORD
