Metadata-Version: 2.4
Name: Furious-GUI
Version: 0.6.1
Summary: A GUI proxy client based on PySide6. Support Xray-core & hysteria
Home-page: https://github.com/LorenEteval/Furious
Author: Loren Eteval
Author-email: loren.eteval@proton.me
License: GPL v3.0
Classifier: Development Status :: 5 - Production/Stable
Classifier: License :: OSI Approved :: GNU General Public License v3 (GPLv3)
Classifier: Intended Audience :: End Users/Desktop
Classifier: Programming Language :: Python :: 3.8
Classifier: Programming Language :: Python :: 3.9
Classifier: Programming Language :: Python :: 3.10
Classifier: Programming Language :: Python :: 3.11
Classifier: Programming Language :: Python :: Implementation :: CPython
Classifier: Programming Language :: Python :: Implementation :: PyPy
Classifier: Operating System :: OS Independent
Classifier: Topic :: Internet
Classifier: Topic :: Internet :: Proxy Servers
License-File: LICENSE
License-File: LICENSE.rtf
Requires-Dist: PySide6-Essentials
Requires-Dist: qdarkstyle
Requires-Dist: ujson
Requires-Dist: pybase64
Requires-Dist: pyqrcode
Requires-Dist: pypng
Requires-Dist: icmplib
Requires-Dist: mss
Requires-Dist: zxing-cpp
Requires-Dist: pillow
Requires-Dist: sysproxy; sys_platform == "win32"
Requires-Dist: win32session; sys_platform == "win32"
Requires-Dist: darkdetect; sys_platform != "darwin"
Requires-Dist: darkdetect[macos-listener]; sys_platform == "darwin"
Requires-Dist: pyobjc-core; sys_platform == "darwin"
Requires-Dist: pyobjc-framework-Cocoa; sys_platform == "darwin"
Dynamic: author
Dynamic: author-email
Dynamic: classifier
Dynamic: description
Dynamic: description-content-type
Dynamic: home-page
Dynamic: license
Dynamic: license-file
Dynamic: requires-dist
Dynamic: summary
